django_integrity/__init__.py
django_integrity/constraints.py
django_integrity/conversion.py
django_integrity/py.typed
django_integrity-0.2.0.dist-info/LICENSE
django_integrity-0.2.0.dist-info/METADATA
django_integrity-0.2.0.dist-info/WHEEL
django_integrity-0.2.0.dist-info/top_level.txt
django_integrity-0.2.0.dist-info/RECORD
