Metadata-Version: 2.1
Name: django_integrity
Version: 0.2.0
Summary: Tools for refining Django's IntegrityError, and working with deferred database constraints.
License: BSD 3-Clause License
Project-URL: repository, https://github.com/kraken-tech/django-integrity
Project-URL: changelog, https://github.com/kraken-tech/django-integrity/blob/main/CHANGELOG.md
Classifier: Development Status :: 3 - Alpha
Classifier: Intended Audience :: Developers
Classifier: License :: OSI Approved :: BSD License
Classifier: Operating System :: OS Independent
Classifier: Programming Language :: Python :: 3
Classifier: Programming Language :: Python :: 3.10
Classifier: Programming Language :: Python :: 3.11
Classifier: Programming Language :: Python :: 3.12
Classifier: Programming Language :: Python :: 3 :: Only
Classifier: Typing :: Typed
Requires-Python: >=3.10
License-File: LICENSE
Provides-Extra: dev
Requires-Dist: dj-database-url >=2.1.0 ; extra == 'dev'
Requires-Dist: django >=4.2.0 ; extra == 'dev'
Requires-Dist: django-stubs >=5.0.0 ; extra == 'dev'
Requires-Dist: environs >=11.0.0 ; extra == 'dev'
Requires-Dist: psycopg2-binary >=2.9.9 ; extra == 'dev'
Requires-Dist: psycopg[binary] >=3.1.18 ; extra == 'dev'
Requires-Dist: pytest-django >=4.8.0 ; extra == 'dev'
Requires-Dist: pytest >=8.2.0 ; extra == 'dev'
Requires-Dist: tox >=4.15.0 ; extra == 'dev'
Requires-Dist: types-psycopg2 >=2.9.21.20240417 ; extra == 'dev'
Requires-Dist: mypy >=1.10.0 ; extra == 'dev'
Requires-Dist: mypy-json-report >=1.2.0 ; extra == 'dev'
Requires-Dist: pre-commit >=3.7.0 ; extra == 'dev'
Requires-Dist: packaging >=24.0 ; extra == 'dev'
Requires-Dist: rich >=13.7.1 ; extra == 'dev'
Requires-Dist: typer >=0.12.3 ; extra == 'dev'
Requires-Dist: tomli >=1.1.0 ; (python_version < "3.11") and extra == 'dev'
Provides-Extra: pytest-in-tox
Requires-Dist: dj-database-url >=2.1.0 ; extra == 'pytest-in-tox'
Requires-Dist: django-stubs >=5.0.0 ; extra == 'pytest-in-tox'
Requires-Dist: environs >=11.0.0 ; extra == 'pytest-in-tox'
Requires-Dist: pytest-django >=4.8.0 ; extra == 'pytest-in-tox'
Requires-Dist: pytest >=8.2.0 ; extra == 'pytest-in-tox'
Provides-Extra: release
Requires-Dist: packaging >=24.0 ; extra == 'release'
Requires-Dist: rich >=13.7.1 ; extra == 'release'
Requires-Dist: typer >=0.12.3 ; extra == 'release'
Requires-Dist: tomli >=1.1.0 ; (python_version < "3.11") and extra == 'release'
Provides-Extra: tox
Requires-Dist: tox-uv >=1.8.2 ; extra == 'tox'
Requires-Dist: tox >=4.15.0 ; extra == 'tox'
